lightprotobuf/__init__.py
lightprotobuf/lightprotobuf.py
lightprotobuf-1.0b1.dist-info/DESCRIPTION.rst
lightprotobuf-1.0b1.dist-info/metadata.json
lightprotobuf-1.0b1.dist-info/RECORD
lightprotobuf-1.0b1.dist-info/top_level.txt
lightprotobuf-1.0b1.dist-info/METADATA
lightprotobuf-1.0b1.dist-info/WHEEL
