Metadata-Version: 2.0
Name: lightprotobuf
Version: 1.0b1
Summary: A light full Python3 Protocol Buffers implementation
Home-page: https://github.com/hl037/lightprotobuf
Author: Léo Flaventin Hauchecorne
Author-email: hl037.prog@gmail.com
License: LGPL3
Keywords: protobuf protocol buffers communication
Platform: UNKNOWN
Classifier: Development Status :: 4 - Beta
Classifier: Intended Audience :: Developers
Classifier: Topic :: Communications
Classifier: Topic :: Internet
Classifier: License :: OSI Approved :: GNU Lesser General Public License v3 or later (LGPLv3+)
Classifier: Programming Language :: Python :: 3
Classifier: Programming Language :: Python :: 3.2
Classifier: Programming Language :: Python :: 3.3
Classifier: Programming Language :: Python :: 3.4
Classifier: Programming Language :: Python :: 3 :: Only
